{
  "id": "N06_112",
  "title": "Движение резерва по сомнительным долгам (авансы)",
  "category": "N06",
  "pages": 2,
  "pdfFile": "1@1_N06_112.pdf",
  "meta": {
    "organization": "",
    "enterpriseCode": "1@1",
    "periodStart": "",
    "periodEnd": "",
    "unit": "тыс.руб."
  },
  "columns": [
    {
      "key": "num",
      "label": "№",
      "type": "text",
      "width": 55,
      "frozen": true,
      "readonly": true
    },
    {
      "key": "name",
      "label": "Наименование показателя",
      "type": "text",
      "width": 320,
      "frozen": true,
      "readonly": true
    },
    {
      "key": "B",
      "label": "Графа B",
      "type": "number"
    },
    {
      "key": "C",
      "label": "Графа C",
      "type": "number"
    },
    {
      "key": "D",
      "label": "Графа D",
      "type": "number"
    },
    {
      "key": "E",
      "label": "Графа E",
      "type": "number"
    },
    {
      "key": "F",
      "label": "Графа F",
      "type": "number"
    },
    {
      "key": "G",
      "label": "Графа G",
      "type": "number"
    },
    {
      "key": "H",
      "label": "Графа H",
      "type": "number"
    },
    {
      "key": "I",
      "label": "Графа I",
      "type": "number"
    }
  ],
  "rows": [
    {
      "num": "10",
      "name": "Резерв по авансам выданным, отраженным в строке 1190 баланса"
    },
    {
      "num": "50",
      "name": "за объекты ОС, МОС, НЗС и оборудования, НМА, малоценные НМА"
    },
    {
      "num": "55",
      "name": "капитальное строительство производственных объектов"
    },
    {
      "num": "60",
      "name": "капитальное строительство непроизводственных объектов"
    },
    {
      "num": "61",
      "name": "за регулярные плановые кап.ремонты, тех.осмотры и тех.обслуживания ОС"
    },
    {
      "num": "99",
      "name": "Итого резерв по авансам выданным, отраженным в строке 1190 баланса"
    },
    {
      "num": "100",
      "name": "Резерв по долгосрочным авансам выданным"
    },
    {
      "num": "105",
      "name": "Задолженность, учитываемая на 60 счете"
    },
    {
      "num": "110",
      "name": "за газ"
    },
    {
      "num": "115",
      "name": "за услуги по транспортировке газа"
    },
    {
      "num": "120",
      "name": "за услуги по хранению газа"
    },
    {
      "num": "125",
      "name": "за продукты нефтегазопереработки"
    },
    {
      "num": "130",
      "name": "за нефть"
    },
    {
      "num": "135",
      "name": "за газовый конденсат"
    },
    {
      "num": "140",
      "name": "за услуги по переработке газа, нефти, газ. конден."
    },
    {
      "num": "145",
      "name": "за электрическую энергию и тепловую энергию"
    },
    {
      "num": "165",
      "name": "авансы выданные таможне"
    },
    {
      "num": "170",
      "name": "прочие авансы выданные"
    },
    {
      "num": "175",
      "name": "Итого авансы выданные, учитываемые на сч 60"
    },
    {
      "num": "180",
      "name": "Задолженность, учитываемая на 76 счете"
    },
    {
      "num": "185",
      "name": "расчеты по аренде и прочему имуществу (сч 7650)"
    },
    {
      "num": "190",
      "name": "расчеты по договорам комиссии (сч 7660)"
    },
    {
      "num": "195",
      "name": "прочая на сч 76"
    },
    {
      "num": "197",
      "name": "Итого авансы выданные, учитываемые на сч 76"
    },
    {
      "num": "199",
      "name": "Итого резерв по долгосрочным авансам выданным"
    },
    {
      "num": "200",
      "name": "Резерв по краткосрочным авансам выданным"
    },
    {
      "num": "205",
      "name": "Задолженность, учитываемая на 60 счете"
    },
    {
      "num": "210",
      "name": "за газ"
    },
    {
      "num": "215",
      "name": "за услуги по транспортировке газа"
    },
    {
      "num": "220",
      "name": "за услуги по хранению газа"
    },
    {
      "num": "225",
      "name": "за продукты нефтегазопереработки"
    },
    {
      "num": "230",
      "name": "за нефть"
    },
    {
      "num": "235",
      "name": "за газовый конденсат"
    },
    {
      "num": "240",
      "name": "за услуги по переработке газа, нефти, газ. конден."
    },
    {
      "num": "245",
      "name": "за электрическую энергию и тепловую энергию"
    },
    {
      "num": "265",
      "name": "авансы выданные таможне"
    },
    {
      "num": "270",
      "name": "прочие авансы выданные"
    },
    {
      "num": "275",
      "name": "Итого авансы выданные, учитываемые на сч 60"
    },
    {
      "num": "280",
      "name": "Задолженность, учитываемая на 76 счете"
    },
    {
      "num": "285",
      "name": "расчеты по аренде и прочему имуществу (сч 7650)"
    },
    {
      "num": "290",
      "name": "расчеты по договорам комиссии (сч 7660)"
    },
    {
      "num": "295",
      "name": "прочая на сч 76"
    },
    {
      "num": "297",
      "name": "Итого авансы выданные, учитываемые на сч 76"
    },
    {
      "num": "299",
      "name": "Итого резерв по краткосрочным авансам выданным"
    },
    {
      "num": "300",
      "name": "ИТОГО"
    }
  ],
  "allowAddRows": false,
  "signatures": [
    "Руководитель",
    "Главный бухгалтер"
  ]
}